{
    "animal_1_n24_04102017_cel1-cor-rep1": {
        "dend": {
            "area": 5490.377911689724,
            "breadth": 7,
            "contrac": 0.8812944939663875,
            "degree": 2,
            "diam": 0.5429645712503769,
            "dist": 147.31031390430542,
            "length": 2806.098854997457,
            "nbranch": 22,
            "nstem": 5,
            "nterm": 27,
            "order": 5,
            "path": 190.31457779029927,
            "seclen": 57.26732357137667,
            "volume": 1608.9476462705063,
            "xdim": 243.558,
            "ydim": 270.668,
            "zdim": 184.0938
        }
    },
    "animal_1_n24_04102017_cel1-cor-rep10": {
        "dend": {
            "area": 5725.4710364298235,
            "breadth": 7,
            "contrac": 0.8844137218593234,
            "degree": 2,
            "diam": 0.5014094711588606,
            "dist": 171.51282453312348,
            "length": 3135.634883370432,
            "nbranch": 27,
            "nstem": 5,
            "nterm": 32,
            "order": 6,
            "path": 228.35622414473121,
            "seclen": 53.146353955431046,
            "volume": 1620.2186038677928,
            "xdim": 197.9212,
            "ydim": 289.113,
            "zdim": 159.6236
        }
    },
    "animal_1_n24_04102017_cel1-cor-rep11": {
        "dend": {
            "area": 5535.262952772509,
            "breadth": 7,
            "contrac": 0.8808307785460266,
            "degree": 2,
            "diam": 0.5460414258290273,
            "dist": 142.96089491399385,
            "length": 2850.583533380102,
            "nbranch": 22,
            "nstem": 5,
            "nterm": 27,
            "order": 5,
            "path": 190.31457779029927,
            "seclen": 58.175174150614325,
            "volume": 1613.9388439078948,
            "xdim": 214.4839,
            "ydim": 255.75900000000001,
            "zdim": 152.0608
        }
    },
    "animal_1_n24_04102017_cel1-cor-rep12": {
        "dend": {
            "area": 5800.881561154969,
            "breadth": 7,
            "contrac": 0.8825235878285431,
            "degree": 2,
            "diam": 0.580730512223316,
            "dist": 142.96089491399385,
            "length": 2884.4167459466807,
            "nbranch": 21,
            "nstem": 5,
            "nterm": 26,
            "order": 5,
            "path": 190.31457779029927,
            "seclen": 61.37056906269534,
            "volume": 1678.6212314127279,
            "xdim": 210.512,
            "ydim": 234.841,
            "zdim": 178.1995
        }
    },
    "animal_1_n24_04102017_cel1-cor-rep13": {
        "dend": {
            "area": 4955.254814420409,
            "breadth": 7,
            "contrac": 0.8837348116640379,
            "degree": 2,
            "diam": 0.5897421151909692,
            "dist": 142.96089491399385,
            "length": 2294.5263583974497,
            "nbranch": 18,
            "nstem": 5,
            "nterm": 23,
            "order": 5,
            "path": 190.31457779029927,
            "seclen": 55.96405752188902,
            "volume": 1559.29849362588,
            "xdim": 175.717,
            "ydim": 244.953,
            "zdim": 116.5622
        }
    },
    "animal_1_n24_04102017_cel1-cor-rep14": {
        "dend": {
            "area": 5917.2268089173895,
            "breadth": 8,
            "contrac": 0.8772169971251057,
            "degree": 2,
            "diam": 0.5507188719327226,
            "dist": 151.3331922388476,
            "length": 2885.079751135373,
            "nbranch": 25,
            "nstem": 5,
            "nterm": 30,
            "order": 5,
            "path": 190.31457779029927,
            "seclen": 52.4559954751886,
            "volume": 1693.31506842482,
            "xdim": 196.2108,
            "ydim": 255.42000000000002,
            "zdim": 146.6062
        }
    },
    "animal_1_n24_04102017_cel1-cor-rep15": {
        "dend": {
            "area": 5402.477832816996,
            "breadth": 7,
            "contrac": 0.8830786675502217,
            "degree": 2,
            "diam": 0.5686713669373018,
            "dist": 188.56975847195116,
            "length": 2642.152587978128,
            "nbranch": 20,
            "nstem": 5,
            "nterm": 25,
            "order": 5,
            "path": 216.6501177097998,
            "seclen": 58.71450195506951,
            "volume": 1608.1996152888119,
            "xdim": 197.9212,
            "ydim": 310.13100000000003,
            "zdim": 139.7688
        }
    },
    "animal_1_n24_04102017_cel1-cor-rep16": {
        "dend": {
            "area": 6622.805758052699,
            "breadth": 7,
            "contrac": 0.8759256102944258,
            "degree": 2,
            "diam": 0.5698025065165229,
            "dist": 209.1612172727057,
            "length": 3334.659779978221,
            "nbranch": 24,
            "nstem": 5,
            "nterm": 29,
            "order": 6,
            "path": 246.5452373124603,
            "seclen": 62.918109056192854,
            "volume": 1797.2036432023638,
            "xdim": 221.345,
            "ydim": 340.408,
            "zdim": 163.3638
        }
    },
    "animal_1_n24_04102017_cel1-cor-rep17": {
        "dend": {
            "area": 5888.4953355940515,
            "breadth": 7,
            "contrac": 0.8784426188200914,
            "degree": 2,
            "diam": 0.5756778357506193,
            "dist": 174.1795822512214,
            "length": 2882.1969833130465,
            "nbranch": 21,
            "nstem": 5,
            "nterm": 26,
            "order": 5,
            "path": 208.67268550735858,
            "seclen": 61.32334007049035,
            "volume": 1690.4256373793958,
            "xdim": 212.0313,
            "ydim": 291.789,
            "zdim": 163.3638
        }
    },
    "animal_1_n24_04102017_cel1-cor-rep18": {
        "dend": {
            "area": 5887.071412064336,
            "breadth": 7,
            "contrac": 0.8736766030843266,
            "degree": 2,
            "diam": 0.5550375290661504,
            "dist": 192.0455122907746,
            "length": 3020.8782191200658,
            "nbranch": 23,
            "nstem": 5,
            "nterm": 28,
            "order": 5,
            "path": 226.3639807010591,
            "seclen": 59.23290625725619,
            "volume": 1667.7750128590667,
            "xdim": 175.717,
            "ydim": 315.438,
            "zdim": 182.53199999999998
        }
    },
    "animal_1_n24_04102017_cel1-cor-rep19": {
        "dend": {
            "area": 5940.693899268116,
            "breadth": 7,
            "contrac": 0.8857649996441305,
            "degree": 2,
            "diam": 0.5621616830248797,
            "dist": 159.77142746501488,
            "length": 3005.625191771367,
            "nbranch": 23,
            "nstem": 5,
            "nterm": 28,
            "order": 5,
            "path": 199.10429525209807,
            "seclen": 58.93382728963465,
            "volume": 1687.4524329920264,
            "xdim": 212.0313,
            "ydim": 282.94100000000003,
            "zdim": 163.3638
        }
    },
    "animal_1_n24_04102017_cel1-cor-rep2": {
        "dend": {
            "area": 5148.14522605587,
            "breadth": 7,
            "contrac": 0.8837252310304122,
            "degree": 2,
            "diam": 0.5760819284417833,
            "dist": 187.1889184398011,
            "length": 2428.940421387722,
            "nbranch": 19,
            "nstem": 5,
            "nterm": 24,
            "order": 5,
            "path": 227.0774050632862,
            "seclen": 56.48698654390051,
            "volume": 1583.2903448571747,
            "xdim": 218.702,
            "ydim": 309.726,
            "zdim": 129.9609
        }
    },
    "animal_1_n24_04102017_cel1-cor-rep20": {
        "dend": {
            "area": 5347.194992381533,
            "breadth": 7,
            "contrac": 0.8841327893952714,
            "degree": 2,
            "diam": 0.5528233143200503,
            "dist": 142.96089491399385,
            "length": 2637.8479195599284,
            "nbranch": 23,
            "nstem": 5,
            "nterm": 28,
            "order": 5,
            "path": 190.31457779029927,
            "seclen": 51.72250822666526,
            "volume": 1605.3295586595484,
            "xdim": 197.9212,
            "ydim": 214.051,
            "zdim": 178.3998
        }
    },
    "animal_1_n24_04102017_cel1-cor-rep21": {
        "dend": {
            "area": 5748.322732901123,
            "breadth": 7,
            "contrac": 0.8832092330133811,
            "degree": 2,
            "diam": 0.5659077241069834,
            "dist": 217.9775916305619,
            "length": 2800.666269272664,
            "nbranch": 22,
            "nstem": 5,
            "nterm": 27,
            "order": 6,
            "path": 255.38152999351558,
            "seclen": 57.15645447495233,
            "volume": 1666.6287312297522,
            "xdim": 202.04500000000002,
            "ydim": 354.787,
            "zdim": 159.0038
        }
    },
    "animal_1_n24_04102017_cel1-cor-rep22": {
        "dend": {
            "area": 5847.117045913228,
            "breadth": 7,
            "contrac": 0.8680521622342479,
            "degree": 2,
            "diam": 0.5334091767732677,
            "dist": 159.4805975988929,
            "length": 3046.9941294126106,
            "nbranch": 25,
            "nstem": 5,
            "nterm": 30,
            "order": 5,
            "path": 209.45353118380243,
            "seclen": 55.39989326204746,
            "volume": 1659.0920835586462,
            "xdim": 199.50920000000002,
            "ydim": 269.249,
            "zdim": 188.77429999999998
        }
    },
    "animal_1_n24_04102017_cel1-cor-rep23": {
        "dend": {
            "area": 5305.003434684078,
            "breadth": 7,
            "contrac": 0.8810837012111203,
            "degree": 2,
            "diam": 0.5892206480631041,
            "dist": 142.96089491399385,
            "length": 2531.429051978196,
            "nbranch": 18,
            "nstem": 5,
            "nterm": 23,
            "order": 5,
            "path": 190.31457779029927,
            "seclen": 61.7421719994682,
            "volume": 1605.1855295302232,
            "xdim": 236.835,
            "ydim": 248.348,
            "zdim": 166.2373
        }
    },
    "animal_1_n24_04102017_cel1-cor-rep24": {
        "dend": {
            "area": 5058.02475969133,
            "breadth": 7,
            "contrac": 0.8862094329047976,
            "degree": 2,
            "diam": 0.5898443956100654,
            "dist": 142.96089491399385,
            "length": 2352.2674599625234,
            "nbranch": 18,
            "nstem": 5,
            "nterm": 23,
            "order": 5,
            "path": 190.31457779029927,
            "seclen": 57.37237707225667,
            "volume": 1575.2890327371758,
            "xdim": 214.0602,
            "ydim": 205.824,
            "zdim": 145.8552
        }
    },
    "animal_1_n24_04102017_cel1-cor-rep25": {
        "dend": {
            "area": 5280.095104744589,
            "breadth": 7,
            "contrac": 0.8843497733375922,
            "degree": 2,
            "diam": 0.5548128156107647,
            "dist": 185.10140879834384,
            "length": 2604.668795846785,
            "nbranch": 21,
            "nstem": 5,
            "nterm": 26,
            "order": 5,
            "path": 230.58236262805727,
            "seclen": 55.4184850180167,
            "volume": 1591.244231145355,
            "xdim": 245.862,
            "ydim": 307.762,
            "zdim": 163.769
        }
    },
    "animal_1_n24_04102017_cel1-cor-rep26": {
        "dend": {
            "area": 5640.623804671029,
            "breadth": 7,
            "contrac": 0.880895079866302,
            "degree": 2,
            "diam": 0.557243602174855,
            "dist": 185.10140879834384,
            "length": 2900.528133745936,
            "nbranch": 21,
            "nstem": 5,
            "nterm": 26,
            "order": 5,
            "path": 230.58236262805727,
            "seclen": 61.71336454778587,
            "volume": 1631.946044831139,
            "xdim": 238.513,
            "ydim": 307.762,
            "zdim": 184.13940000000002
        }
    },
    "animal_1_n24_04102017_cel1-cor-rep27": {
        "dend": {
            "area": 5601.721858806596,
            "breadth": 7,
            "contrac": 0.8852902430004521,
            "degree": 2,
            "diam": 0.5691157151614975,
            "dist": 186.15787129425925,
            "length": 2787.2207890939185,
            "nbranch": 22,
            "nstem": 5,
            "nterm": 27,
            "order": 5,
            "path": 222.52321967914727,
            "seclen": 56.88205692028405,
            "volume": 1630.768510210185,
            "xdim": 181.5367,
            "ydim": 307.877,
            "zdim": 174.793
        }
    },
    "animal_1_n24_04102017_cel1-cor-rep28": {
        "dend": {
            "area": 6620.402506359418,
            "breadth": 7,
            "contrac": 0.8708081190510466,
            "degree": 2,
            "diam": 0.5688249997424379,
            "dist": 207.0098400580272,
            "length": 3371.759577130052,
            "nbranch": 25,
            "nstem": 5,
            "nterm": 30,
            "order": 6,
            "path": 263.6733272517636,
            "seclen": 61.30471958418276,
            "volume": 1794.0273957615168,
            "xdim": 215.324,
            "ydim": 371.964,
            "zdim": 154.10590000000002
        }
    },
    "animal_1_n24_04102017_cel1-cor-rep29": {
        "dend": {
            "area": 5792.269036128931,
            "breadth": 7,
            "contrac": 0.875520297774156,
            "degree": 2,
            "diam": 0.5512114629200093,
            "dist": 215.52171382088164,
            "length": 2894.0173035436956,
            "nbranch": 25,
            "nstem": 5,
            "nterm": 30,
            "order": 6,
            "path": 272.5102600184652,
            "seclen": 52.61849642806719,
            "volume": 1665.3641874615628,
            "xdim": 179.4912,
            "ydim": 336.429,
            "zdim": 132.2254
        }
    },
    "animal_1_n24_04102017_cel1-cor-rep3": {
        "dend": {
            "area": 5927.067874589512,
            "breadth": 8,
            "contrac": 0.8809564716736704,
            "degree": 2,
            "diam": 0.5334758142738932,
            "dist": 173.36116315078328,
            "length": 3072.593670744188,
            "nbranch": 26,
            "nstem": 5,
            "nterm": 31,
            "order": 6,
            "path": 228.6898942399139,
            "seclen": 53.90515211831909,
            "volume": 1665.3036776814192,
            "xdim": 219.586,
            "ydim": 271.78000000000003,
            "zdim": 147.3899
        }
    },
    "animal_1_n24_04102017_cel1-cor-rep30": {
        "dend": {
            "area": 4939.1079432412225,
            "breadth": 7,
            "contrac": 0.893032224938271,
            "degree": 2,
            "diam": 0.5559359579180547,
            "dist": 142.96089491399385,
            "length": 2432.435090566714,
            "nbranch": 20,
            "nstem": 5,
            "nterm": 25,
            "order": 5,
            "path": 190.31457779029927,
            "seclen": 54.05411312370475,
            "volume": 1538.0010002354536,
            "xdim": 175.717,
            "ydim": 246.64800000000002,
            "zdim": 132.0826
        }
    },
    "animal_1_n24_04102017_cel1-cor-rep31": {
        "dend": {
            "area": 5745.25526024578,
            "breadth": 7,
            "contrac": 0.8767317572508058,
            "degree": 2,
            "diam": 0.5207083413251359,
            "dist": 166.138094653484,
            "length": 3049.0423928253776,
            "nbranch": 26,
            "nstem": 5,
            "nterm": 31,
            "order": 6,
            "path": 209.99786522888476,
            "seclen": 53.491971803953994,
            "volume": 1635.3835396613956,
            "xdim": 237.87900000000002,
            "ydim": 287.731,
            "zdim": 180.6626
        }
    },
    "animal_1_n24_04102017_cel1-cor-rep32": {
        "dend": {
            "area": 5912.936216275236,
            "breadth": 8,
            "contrac": 0.8776537767189141,
            "degree": 2,
            "diam": 0.5406721396027095,
            "dist": 153.10014712690517,
            "length": 2990.377822120526,
            "nbranch": 26,
            "nstem": 5,
            "nterm": 31,
            "order": 6,
            "path": 190.31457779029927,
            "seclen": 52.46276880913204,
            "volume": 1677.6793482200483,
            "xdim": 206.9546,
            "ydim": 238.804,
            "zdim": 141.6021
        }
    },
    "animal_1_n24_04102017_cel1-cor-rep33": {
        "dend": {
            "area": 5904.161392513734,
            "breadth": 9,
            "contrac": 0.895313687276103,
            "degree": 2,
            "diam": 0.5174123810733888,
            "dist": 166.7820874645203,
            "length": 3210.8195865113726,
            "nbranch": 27,
            "nstem": 5,
            "nterm": 32,
            "order": 6,
            "path": 214.69612370185186,
            "seclen": 54.42067095781987,
            "volume": 1638.5350678408438,
            "xdim": 184.4203,
            "ydim": 277.391,
            "zdim": 205.2307
        }
    },
    "animal_1_n24_04102017_cel1-cor-rep34": {
        "dend": {
            "area": 6793.931117633545,
            "breadth": 8,
            "contrac": 0.8704747238128009,
            "degree": 2,
            "diam": 0.5553319286792043,
            "dist": 209.1612172727057,
            "length": 3443.1427925555,
            "nbranch": 27,
            "nstem": 5,
            "nterm": 32,
            "order": 6,
            "path": 248.56523819586315,
            "seclen": 58.35835241619491,
            "volume": 1827.805322530104,
            "xdim": 221.994,
            "ydim": 376.096,
            "zdim": 166.3773
        }
    },
    "animal_1_n24_04102017_cel1-cor-rep35": {
        "dend": {
            "area": 6510.161340707943,
            "breadth": 8,
            "contrac": 0.8819467639474623,
            "degree": 2,
            "diam": 0.5293780007887858,
            "dist": 190.0900863334277,
            "length": 3597.465886430702,
            "nbranch": 27,
            "nstem": 5,
            "nterm": 32,
            "order": 6,
            "path": 227.0774050632862,
            "seclen": 60.973998075096645,
            "volume": 1726.0269535217244,
            "xdim": 220.506,
            "ydim": 333.771,
            "zdim": 160.4916
        }
    },
    "animal_1_n24_04102017_cel1-cor-rep36": {
        "dend": {
            "area": 5870.532680611261,
            "breadth": 7,
            "contrac": 0.8815678815861807,
            "degree": 2,
            "diam": 0.5902533067672521,
            "dist": 177.02081767408035,
            "length": 2843.5254244647235,
            "nbranch": 20,
            "nstem": 5,
            "nterm": 25,
            "order": 5,
            "path": 199.17477810924257,
            "seclen": 63.18945387699386,
            "volume": 1695.9918319739058,
            "xdim": 196.8852,
            "ydim": 290.297,
            "zdim": 152.6282
        }
    },
    "animal_1_n24_04102017_cel1-cor-rep37": {
        "dend": {
            "area": 5667.374825323925,
            "breadth": 9,
            "contrac": 0.8805279095659946,
            "degree": 2,
            "diam": 0.5411315310603583,
            "dist": 174.1795822512214,
            "length": 2894.462197395243,
            "nbranch": 23,
            "nstem": 5,
            "nterm": 28,
            "order": 6,
            "path": 207.20322929806835,
            "seclen": 56.75416073324006,
            "volume": 1632.0310308079218,
            "xdim": 229.024,
            "ydim": 271.61199999999997,
            "zdim": 157.5737
        }
    },
    "animal_1_n24_04102017_cel1-cor-rep38": {
        "dend": {
            "area": 5975.538813854008,
            "breadth": 7,
            "contrac": 0.8799092858383811,
            "degree": 2,
            "diam": 0.5642907494939398,
            "dist": 209.1612172727057,
            "length": 2974.1733216628804,
            "nbranch": 22,
            "nstem": 5,
            "nterm": 27,
            "order": 6,
            "path": 246.5452373124603,
            "seclen": 60.697414727813886,
            "volume": 1695.7870610277157,
            "xdim": 221.994,
            "ydim": 304.073,
            "zdim": 141.6526
        }
    },
    "animal_1_n24_04102017_cel1-cor-rep39": {
        "dend": {
            "area": 5385.935212242282,
            "breadth": 7,
            "contrac": 0.8744229338486502,
            "degree": 2,
            "diam": 0.5658762801375509,
            "dist": 148.8881000158844,
            "length": 2609.414254562105,
            "nbranch": 22,
            "nstem": 5,
            "nterm": 27,
            "order": 5,
            "path": 190.31457779029927,
            "seclen": 53.25335213392051,
            "volume": 1615.4707867697941,
            "xdim": 175.717,
            "ydim": 272.008,
            "zdim": 130.1192
        }
    },
    "animal_1_n24_04102017_cel1-cor-rep4": {
        "dend": {
            "area": 5263.350908993262,
            "breadth": 7,
            "contrac": 0.8863543751232312,
            "degree": 2,
            "diam": 0.5653225829925609,
            "dist": 153.4011369200698,
            "length": 2553.871326234085,
            "nbranch": 20,
            "nstem": 5,
            "nterm": 25,
            "order": 5,
            "path": 190.31457779029927,
            "seclen": 56.75269613853522,
            "volume": 1596.2270947183947,
            "xdim": 175.717,
            "ydim": 254.834,
            "zdim": 178.3998
        }
    },
    "animal_1_n24_04102017_cel1-cor-rep40": {
        "dend": {
            "area": 6332.358609282376,
            "breadth": 7,
            "contrac": 0.8859473596859219,
            "degree": 2,
            "diam": 0.5267071175247773,
            "dist": 212.8095320693131,
            "length": 3331.2458384851693,
            "nbranch": 27,
            "nstem": 5,
            "nterm": 32,
            "order": 5,
            "path": 273.3886923002496,
            "seclen": 56.46179387262999,
            "volume": 1723.916030970553,
            "xdim": 253.361,
            "ydim": 335.05,
            "zdim": 190.9367
        }
    },
    "animal_1_n24_04102017_cel1-cor-rep41": {
        "dend": {
            "area": 5347.696468742333,
            "breadth": 7,
            "contrac": 0.8855403123513302,
            "degree": 2,
            "diam": 0.5634177674675327,
            "dist": 142.96089491399385,
            "length": 2607.630428063359,
            "nbranch": 20,
            "nstem": 5,
            "nterm": 25,
            "order": 5,
            "path": 190.31457779029927,
            "seclen": 57.94734284585242,
            "volume": 1604.155863271077,
            "xdim": 197.7414,
            "ydim": 239.708,
            "zdim": 143.6932
        }
    },
    "animal_1_n24_04102017_cel1-cor-rep42": {
        "dend": {
            "area": 5481.468620515091,
            "breadth": 8,
            "contrac": 0.8762024669088803,
            "degree": 2,
            "diam": 0.5683328990475354,
            "dist": 144.13588769469453,
            "length": 2607.5915266898714,
            "nbranch": 22,
            "nstem": 5,
            "nterm": 27,
            "order": 5,
            "path": 190.31457779029927,
            "seclen": 53.21615360591574,
            "volume": 1634.4447839835168,
            "xdim": 196.2108,
            "ydim": 278.233,
            "zdim": 135.4278
        }
    },
    "animal_1_n24_04102017_cel1-cor-rep43": {
        "dend": {
            "area": 5895.358415402161,
            "breadth": 7,
            "contrac": 0.8765201240694864,
            "degree": 2,
            "diam": 0.571554618316287,
            "dist": 198.66783196179495,
            "length": 2900.9103361024663,
            "nbranch": 21,
            "nstem": 5,
            "nterm": 26,
            "order": 6,
            "path": 234.59100643279496,
            "seclen": 61.72149651281843,
            "volume": 1693.2879959775723,
            "xdim": 219.03300000000002,
            "ydim": 316.224,
            "zdim": 145.8552
        }
    },
    "animal_1_n24_04102017_cel1-cor-rep44": {
        "dend": {
            "area": 6393.609183751662,
            "breadth": 7,
            "contrac": 0.8780318825350971,
            "degree": 2,
            "diam": 0.5280596628767523,
            "dist": 207.0098400580272,
            "length": 3474.88632441971,
            "nbranch": 27,
            "nstem": 5,
            "nterm": 32,
            "order": 6,
            "path": 263.6733272517636,
            "seclen": 58.896378379995085,
            "volume": 1707.2983718399146,
            "xdim": 222.67700000000002,
            "ydim": 337.43600000000004,
            "zdim": 154.10590000000002
        }
    },
    "animal_1_n24_04102017_cel1-cor-rep45": {
        "dend": {
            "area": 5687.226697069859,
            "breadth": 8,
            "contrac": 0.8762445584541212,
            "degree": 2,
            "diam": 0.5542198326845675,
            "dist": 207.0098400580272,
            "length": 2872.202298758307,
            "nbranch": 23,
            "nstem": 5,
            "nterm": 28,
            "order": 6,
            "path": 263.6733272517636,
            "seclen": 56.31769213251582,
            "volume": 1642.1124093697556,
            "xdim": 245.862,
            "ydim": 273.592,
            "zdim": 163.769
        }
    },
    "animal_1_n24_04102017_cel1-cor-rep46": {
        "dend": {
            "area": 5577.2478648040205,
            "breadth": 7,
            "contrac": 0.8738319456351642,
            "degree": 2,
            "diam": 0.5765407653251569,
            "dist": 165.38569564711455,
            "length": 2676.2005355841807,
            "nbranch": 22,
            "nstem": 5,
            "nterm": 27,
            "order": 5,
            "path": 214.00564270363398,
            "seclen": 54.61633746090165,
            "volume": 1665.1704422506534,
            "xdim": 176.9768,
            "ydim": 282.028,
            "zdim": 138.11
        }
    },
    "animal_1_n24_04102017_cel1-cor-rep47": {
        "dend": {
            "area": 5335.0633802575585,
            "breadth": 7,
            "contrac": 0.8786763620268165,
            "degree": 2,
            "diam": 0.5831231302138697,
            "dist": 168.51082481000353,
            "length": 2545.6284450862468,
            "nbranch": 20,
            "nstem": 5,
            "nterm": 25,
            "order": 5,
            "path": 208.67268550735858,
            "seclen": 56.56952100191659,
            "volume": 1616.9003889783514,
            "xdim": 175.717,
            "ydim": 291.789,
            "zdim": 178.4744
        }
    },
    "animal_1_n24_04102017_cel1-cor-rep48": {
        "dend": {
            "area": 6684.345766457648,
            "breadth": 8,
            "contrac": 0.874742655928465,
            "degree": 2,
            "diam": 0.5601870190439402,
            "dist": 246.3387976959393,
            "length": 3472.0871915686002,
            "nbranch": 25,
            "nstem": 5,
            "nterm": 30,
            "order": 6,
            "path": 274.4917629922627,
            "seclen": 63.12885802852001,
            "volume": 1786.9208994261726,
            "xdim": 241.676,
            "ydim": 384.36400000000003,
            "zdim": 176.17669999999998
        }
    },
    "animal_1_n24_04102017_cel1-cor-rep49": {
        "dend": {
            "area": 5244.763522376066,
            "breadth": 7,
            "contrac": 0.8864595584325113,
            "degree": 2,
            "diam": 0.5755342901904575,
            "dist": 142.96089491399385,
            "length": 2540.232496460994,
            "nbranch": 19,
            "nstem": 5,
            "nterm": 24,
            "order": 5,
            "path": 190.31457779029927,
            "seclen": 59.07517433630218,
            "volume": 1588.3600584516512,
            "xdim": 232.898,
            "ydim": 237.532,
            "zdim": 155.2734
        }
    },
    "animal_1_n24_04102017_cel1-cor-rep5": {
        "dend": {
            "area": 5555.453165994776,
            "breadth": 9,
            "contrac": 0.8753721324782361,
            "degree": 2,
            "diam": 0.5441968069442145,
            "dist": 142.96089491399385,
            "length": 2869.2875110856316,
            "nbranch": 24,
            "nstem": 5,
            "nterm": 29,
            "order": 6,
            "path": 190.31457779029927,
            "seclen": 54.13750020916286,
            "volume": 1619.7520765576878,
            "xdim": 196.155,
            "ydim": 248.348,
            "zdim": 131.7442
        }
    },
    "animal_1_n24_04102017_cel1-cor-rep50": {
        "dend": {
            "area": 5688.909426713683,
            "breadth": 7,
            "contrac": 0.8793942072629142,
            "degree": 2,
            "diam": 0.5720789839378517,
            "dist": 151.73030593913302,
            "length": 2813.352199526226,
            "nbranch": 21,
            "nstem": 5,
            "nterm": 26,
            "order": 5,
            "path": 190.31457779029927,
            "seclen": 59.85855743672821,
            "volume": 1649.737651613932,
            "xdim": 198.06040000000002,
            "ydim": 278.92100000000005,
            "zdim": 152.6282
        }
    },
    "animal_1_n24_04102017_cel1-cor-rep51": {
        "dend": {
            "area": 6397.454895043047,
            "breadth": 7,
            "contrac": 0.8798579039989636,
            "degree": 2,
            "diam": 0.5596984805291757,
            "dist": 222.36708634166163,
            "length": 3218.9137725748847,
            "nbranch": 25,
            "nstem": 5,
            "nterm": 30,
            "order": 6,
            "path": 272.8693320275461,
            "seclen": 58.525704955906996,
            "volume": 1750.9920493727627,
            "xdim": 230.81400000000002,
            "ydim": 420.709,
            "zdim": 160.4495
        }
    },
    "animal_1_n24_04102017_cel1-cor-rep52": {
        "dend": {
            "area": 5761.736977387929,
            "breadth": 7,
            "contrac": 0.8785668332625496,
            "degree": 2,
            "diam": 0.5407321172850859,
            "dist": 226.72684123722536,
            "length": 2911.513556774872,
            "nbranch": 24,
            "nstem": 5,
            "nterm": 29,
            "order": 5,
            "path": 272.893879724851,
            "seclen": 54.93421805235608,
            "volume": 1657.230068456011,
            "xdim": 197.9212,
            "ydim": 346.02,
            "zdim": 140.8107
        }
    },
    "animal_1_n24_04102017_cel1-cor-rep53": {
        "dend": {
            "area": 5542.173310888339,
            "breadth": 7,
            "contrac": 0.8942760290096124,
            "degree": 2,
            "diam": 0.5489434220798782,
            "dist": 163.3605832997939,
            "length": 2879.9438583403244,
            "nbranch": 23,
            "nstem": 5,
            "nterm": 28,
            "order": 5,
            "path": 190.31457779029927,
            "seclen": 56.46948741843773,
            "volume": 1606.8202653501462,
            "xdim": 237.87900000000002,
            "ydim": 286.132,
            "zdim": 180.6626
        }
    },
    "animal_1_n24_04102017_cel1-cor-rep54": {
        "dend": {
            "area": 5563.183447640011,
            "breadth": 7,
            "contrac": 0.8793978092428353,
            "degree": 2,
            "diam": 0.5950682136589829,
            "dist": 152.83109355095252,
            "length": 2623.0511896683565,
            "nbranch": 19,
            "nstem": 5,
            "nterm": 24,
            "order": 5,
            "path": 194.12995672849522,
            "seclen": 61.00119045740364,
            "volume": 1661.7921717578417,
            "xdim": 223.86200000000002,
            "ydim": 249.639,
            "zdim": 141.7363
        }
    },
    "animal_1_n24_04102017_cel1-cor-rep55": {
        "dend": {
            "area": 6178.302134963296,
            "breadth": 10,
            "contrac": 0.8803181487138416,
            "degree": 2,
            "diam": 0.5316266835428848,
            "dist": 243.69764573596112,
            "length": 3338.2922127609613,
            "nbranch": 26,
            "nstem": 5,
            "nterm": 31,
            "order": 8,
            "path": 279.9519348497326,
            "seclen": 58.56653004843792,
            "volume": 1683.0820198179006,
            "xdim": 250.752,
            "ydim": 370.377,
            "zdim": 186.6567
        }
    },
    "animal_1_n24_04102017_cel1-cor-rep56": {
        "dend": {
            "area": 5714.750303617753,
            "breadth": 9,
            "contrac": 0.8836788885528823,
            "degree": 2,
            "diam": 0.5303285951809847,
            "dist": 171.51282453312348,
            "length": 2990.5202888225153,
            "nbranch": 25,
            "nstem": 5,
            "nterm": 30,
            "order": 6,
            "path": 228.35622414473121,
            "seclen": 54.37309616040937,
            "volume": 1633.5130684051223,
            "xdim": 202.0533,
            "ydim": 289.113,
            "zdim": 150.4604
        }
    },
    "animal_1_n24_04102017_cel1-cor-rep57": {
        "dend": {
            "area": 5060.135854872741,
            "breadth": 7,
            "contrac": 0.8871662109186853,
            "degree": 2,
            "diam": 0.5561022836100598,
            "dist": 142.96089491399385,
            "length": 2479.818002269018,
            "nbranch": 20,
            "nstem": 5,
            "nterm": 25,
            "order": 5,
            "path": 190.31457779029927,
            "seclen": 55.10706671708929,
            "volume": 1561.368784192617,
            "xdim": 175.717,
            "ydim": 246.64800000000002,
            "zdim": 132.0826
        }
    },
    "animal_1_n24_04102017_cel1-cor-rep58": {
        "dend": {
            "area": 5259.579596377584,
            "breadth": 7,
            "contrac": 0.8812182180503935,
            "degree": 2,
            "diam": 0.5690111821232117,
            "dist": 161.14827484433118,
            "length": 2533.440594044545,
            "nbranch": 20,
            "nstem": 5,
            "nterm": 25,
            "order": 6,
            "path": 191.7033678415073,
            "seclen": 56.29867986765655,
            "volume": 1599.9886026827992,
            "xdim": 201.0198,
            "ydim": 256.784,
            "zdim": 146.8227
        }
    },
    "animal_1_n24_04102017_cel1-cor-rep59": {
        "dend": {
            "area": 5929.489712145812,
            "breadth": 9,
            "contrac": 0.8891097895178313,
            "degree": 2,
            "diam": 0.5174923536411064,
            "dist": 142.96089491399385,
            "length": 3136.967777347941,
            "nbranch": 28,
            "nstem": 5,
            "nterm": 33,
            "order": 6,
            "path": 190.31457779029927,
            "seclen": 51.42570126799904,
            "volume": 1655.0561177456964,
            "xdim": 229.024,
            "ydim": 260.986,
            "zdim": 157.5737
        }
    },
    "animal_1_n24_04102017_cel1-cor-rep6": {
        "dend": {
            "area": 5455.322564665696,
            "breadth": 7,
            "contrac": 0.8788939824666282,
            "degree": 2,
            "diam": 0.5750789347798718,
            "dist": 202.3714458940542,
            "length": 2657.3978531094253,
            "nbranch": 20,
            "nstem": 5,
            "nterm": 25,
            "order": 6,
            "path": 242.3832193113624,
            "seclen": 59.053285624653896,
            "volume": 1618.9751120546566,
            "xdim": 194.9624,
            "ydim": 310.399,
            "zdim": 146.5807
        }
    },
    "animal_1_n24_04102017_cel1-cor-rep60": {
        "dend": {
            "area": 5530.171049178358,
            "breadth": 7,
            "contrac": 0.8822262734422364,
            "degree": 2,
            "diam": 0.5506268326945961,
            "dist": 163.5508730668534,
            "length": 2836.9897932136246,
            "nbranch": 23,
            "nstem": 5,
            "nterm": 28,
            "order": 5,
            "path": 197.438451805751,
            "seclen": 55.627250847325975,
            "volume": 1622.7542366170908,
            "xdim": 196.9615,
            "ydim": 279.741,
            "zdim": 160.4916
        }
    },
    "animal_1_n24_04102017_cel1-cor-rep61": {
        "dend": {
            "area": 5400.168326997017,
            "breadth": 7,
            "contrac": 0.8879175342504674,
            "degree": 2,
            "diam": 0.5782750547693591,
            "dist": 151.3821190192689,
            "length": 2550.181031055865,
            "nbranch": 21,
            "nstem": 5,
            "nterm": 26,
            "order": 5,
            "path": 190.31457779029927,
            "seclen": 54.25917087352904,
            "volume": 1627.6942417791709,
            "xdim": 230.68,
            "ydim": 273.41700000000003,
            "zdim": 159.4229
        }
    },
    "animal_1_n24_04102017_cel1-cor-rep62": {
        "dend": {
            "area": 6000.90475990965,
            "breadth": 7,
            "contrac": 0.8829922266005729,
            "degree": 2,
            "diam": 0.5475208747004282,
            "dist": 246.3387976959393,
            "length": 3089.5551163504497,
            "nbranch": 24,
            "nstem": 5,
            "nterm": 29,
            "order": 6,
            "path": 274.4917629922627,
            "seclen": 58.29349276132924,
            "volume": 1689.044642666394,
            "xdim": 220.506,
            "ydim": 393.685,
            "zdim": 158.4312
        }
    },
    "animal_1_n24_04102017_cel1-cor-rep63": {
        "dend": {
            "area": 5941.224198319279,
            "breadth": 8,
            "contrac": 0.8885268330394167,
            "degree": 2,
            "diam": 0.5501727697505202,
            "dist": 226.72684123722536,
            "length": 2956.1032719987165,
            "nbranch": 25,
            "nstem": 5,
            "nterm": 30,
            "order": 5,
            "path": 272.893879724851,
            "seclen": 53.74733221815848,
            "volume": 1686.3563695929445,
            "xdim": 178.3856,
            "ydim": 346.02,
            "zdim": 147.62380000000002
        }
    },
    "animal_1_n24_04102017_cel1-cor-rep64": {
        "dend": {
            "area": 5727.279925357143,
            "breadth": 7,
            "contrac": 0.8824510156258123,
            "degree": 2,
            "diam": 0.5536056898590582,
            "dist": 198.66783196179495,
            "length": 2950.7723588701792,
            "nbranch": 21,
            "nstem": 5,
            "nterm": 26,
            "order": 6,
            "path": 234.59100643279496,
            "seclen": 62.782390614259135,
            "volume": 1650.134928881487,
            "xdim": 218.575,
            "ydim": 347.09299999999996,
            "zdim": 160.4916
        }
    },
    "animal_1_n24_04102017_cel1-cor-rep65": {
        "dend": {
            "area": 5814.7877004749125,
            "breadth": 7,
            "contrac": 0.8827983286491178,
            "degree": 2,
            "diam": 0.5701380926944091,
            "dist": 198.66783196179495,
            "length": 2906.8562006864395,
            "nbranch": 21,
            "nstem": 5,
            "nterm": 26,
            "order": 6,
            "path": 234.59100643279496,
            "seclen": 61.848004269924246,
            "volume": 1672.4794066460831,
            "xdim": 194.4006,
            "ydim": 329.052,
            "zdim": 150.1069
        }
    },
    "animal_1_n24_04102017_cel1-cor-rep66": {
        "dend": {
            "area": 5833.825150136721,
            "breadth": 7,
            "contrac": 0.875320985675644,
            "degree": 2,
            "diam": 0.5137549607752573,
            "dist": 166.7820874645203,
            "length": 3198.4427502514973,
            "nbranch": 27,
            "nstem": 5,
            "nterm": 32,
            "order": 6,
            "path": 214.69612370185186,
            "seclen": 54.210894072059276,
            "volume": 1626.2907893575352,
            "xdim": 202.214,
            "ydim": 277.391,
            "zdim": 187.5052
        }
    },
    "animal_1_n24_04102017_cel1-cor-rep67": {
        "dend": {
            "area": 5663.697438132629,
            "breadth": 7,
            "contrac": 0.8918975336375037,
            "degree": 2,
            "diam": 0.5674718588243846,
            "dist": 164.61600919573405,
            "length": 2730.610762202885,
            "nbranch": 22,
            "nstem": 5,
            "nterm": 27,
            "order": 5,
            "path": 205.30757628920944,
            "seclen": 55.72675024903847,
            "volume": 1672.2864594704834,
            "xdim": 206.2834,
            "ydim": 281.121,
            "zdim": 178.3998
        }
    },
    "animal_1_n24_04102017_cel1-cor-rep68": {
        "dend": {
            "area": 4962.725482454375,
            "breadth": 7,
            "contrac": 0.890982337295293,
            "degree": 2,
            "diam": 0.5858757777650605,
            "dist": 142.96089491399385,
            "length": 2282.97940292609,
            "nbranch": 18,
            "nstem": 5,
            "nterm": 23,
            "order": 5,
            "path": 190.31457779029927,
            "seclen": 55.68242446161196,
            "volume": 1564.7366723027792,
            "xdim": 188.1926,
            "ydim": 235.246,
            "zdim": 113.4912
        }
    },
    "animal_1_n24_04102017_cel1-cor-rep69": {
        "dend": {
            "area": 5742.276391577637,
            "breadth": 10,
            "contrac": 0.8882289239376108,
            "degree": 2,
            "diam": 0.5264898014948206,
            "dist": 142.96089491399385,
            "length": 3077.783647356397,
            "nbranch": 26,
            "nstem": 5,
            "nterm": 31,
            "order": 6,
            "path": 190.31457779029927,
            "seclen": 53.996204339585915,
            "volume": 1622.4438279520448,
            "xdim": 214.4839,
            "ydim": 254.837,
            "zdim": 160.8913
        }
    },
    "animal_1_n24_04102017_cel1-cor-rep7": {
        "dend": {
            "area": 5779.781207350172,
            "breadth": 7,
            "contrac": 0.8825070043778402,
            "degree": 2,
            "diam": 0.5769465034434265,
            "dist": 169.98977530752285,
            "length": 2816.2484800615875,
            "nbranch": 23,
            "nstem": 5,
            "nterm": 28,
            "order": 6,
            "path": 200.53975723074615,
            "seclen": 55.22055843258015,
            "volume": 1674.9614927925384,
            "xdim": 184.89690000000002,
            "ydim": 295.155,
            "zdim": 157.5359
        }
    },
    "animal_1_n24_04102017_cel1-cor-rep70": {
        "dend": {
            "area": 5151.41307881128,
            "breadth": 7,
            "contrac": 0.8838509574645406,
            "degree": 2,
            "diam": 0.577288529166638,
            "dist": 142.96089491399385,
            "length": 2473.7442916764517,
            "nbranch": 20,
            "nstem": 5,
            "nterm": 25,
            "order": 5,
            "path": 190.31457779029927,
            "seclen": 54.972095370587816,
            "volume": 1575.3003757683973,
            "xdim": 210.2064,
            "ydim": 205.824,
            "zdim": 152.71120000000002
        }
    },
    "animal_1_n24_04102017_cel1-cor-rep71": {
        "dend": {
            "area": 5733.438900013497,
            "breadth": 7,
            "contrac": 0.8825842667965812,
            "degree": 2,
            "diam": 0.5451624084117516,
            "dist": 151.3331922388476,
            "length": 2938.8149081016277,
            "nbranch": 23,
            "nstem": 5,
            "nterm": 28,
            "order": 5,
            "path": 190.31457779029927,
            "seclen": 57.6238217274829,
            "volume": 1647.0391962362191,
            "xdim": 234.014,
            "ydim": 238.849,
            "zdim": 168.2255
        }
    },
    "animal_1_n24_04102017_cel1-cor-rep72": {
        "dend": {
            "area": 6962.899337826347,
            "breadth": 7,
            "contrac": 0.8792607017736386,
            "degree": 2,
            "diam": 0.6080273118221001,
            "dist": 192.0455122907746,
            "length": 3276.69830372202,
            "nbranch": 24,
            "nstem": 5,
            "nterm": 29,
            "order": 5,
            "path": 226.3639807010591,
            "seclen": 61.82449629664188,
            "volume": 1903.7870267240435,
            "xdim": 230.68,
            "ydim": 315.438,
            "zdim": 188.4984
        }
    },
    "animal_1_n24_04102017_cel1-cor-rep73": {
        "dend": {
            "area": 5581.765077453635,
            "breadth": 8,
            "contrac": 0.8829126954783318,
            "degree": 2,
            "diam": 0.5738741965585851,
            "dist": 151.3821190192689,
            "length": 2692.0834614159276,
            "nbranch": 22,
            "nstem": 5,
            "nterm": 27,
            "order": 5,
            "path": 190.31457779029927,
            "seclen": 54.94047880440669,
            "volume": 1656.9138836628135,
            "xdim": 210.512,
            "ydim": 273.41700000000003,
            "zdim": 178.1995
        }
    },
    "animal_1_n24_04102017_cel1-cor-rep74": {
        "dend": {
            "area": 5395.939830225378,
            "breadth": 7,
            "contrac": 0.8832457057103473,
            "degree": 2,
            "diam": 0.5596838856832308,
            "dist": 212.8095320693131,
            "length": 2631.1601355118287,
            "nbranch": 21,
            "nstem": 5,
            "nterm": 26,
            "order": 5,
            "path": 273.3886923002496,
            "seclen": 55.98213054280487,
            "volume": 1615.953362527641,
            "xdim": 194.9624,
            "ydim": 335.05,
            "zdim": 178.3998
        }
    },
    "animal_1_n24_04102017_cel1-cor-rep75": {
        "dend": {
            "area": 6484.529388295678,
            "breadth": 9,
            "contrac": 0.8849243312571469,
            "degree": 2,
            "diam": 0.5500455616035829,
            "dist": 174.26762165626178,
            "length": 3392.840176318587,
            "nbranch": 28,
            "nstem": 5,
            "nterm": 33,
            "order": 6,
            "path": 210.65570203579412,
            "seclen": 55.6203307593211,
            "volume": 1747.396285979505,
            "xdim": 206.20080000000002,
            "ydim": 292.693,
            "zdim": 182.53199999999998
        }
    },
    "animal_1_n24_04102017_cel1-cor-rep76": {
        "dend": {
            "area": 6122.331339493186,
            "breadth": 7,
            "contrac": 0.8915271133875085,
            "degree": 2,
            "diam": 0.5538973220214318,
            "dist": 169.02615379014574,
            "length": 3087.1144530939614,
            "nbranch": 25,
            "nstem": 5,
            "nterm": 30,
            "order": 5,
            "path": 197.03414355703902,
            "seclen": 56.12935369261748,
            "volume": 1723.5247562463915,
            "xdim": 234.671,
            "ydim": 245.69299999999998,
            "zdim": 174.2209
        }
    },
    "animal_1_n24_04102017_cel1-cor-rep77": {
        "dend": {
            "area": 5863.222006457945,
            "breadth": 8,
            "contrac": 0.8697058040090662,
            "degree": 2,
            "diam": 0.5620396133369246,
            "dist": 210.19698057548305,
            "length": 2882.346447854034,
            "nbranch": 24,
            "nstem": 5,
            "nterm": 29,
            "order": 6,
            "path": 267.8995583696509,
            "seclen": 54.38389524252894,
            "volume": 1681.949918701294,
            "xdim": 204.613,
            "ydim": 330.902,
            "zdim": 156.08960000000002
        }
    },
    "animal_1_n24_04102017_cel1-cor-rep78": {
        "dend": {
            "area": 6169.618239349871,
            "breadth": 10,
            "contrac": 0.8829326011419449,
            "degree": 2,
            "diam": 0.5554544761212644,
            "dist": 243.69764573596112,
            "length": 3162.0564815245793,
            "nbranch": 24,
            "nstem": 5,
            "nterm": 29,
            "order": 8,
            "path": 279.9519348497326,
            "seclen": 59.661443047633576,
            "volume": 1719.4422072152931,
            "xdim": 250.752,
            "ydim": 357.164,
            "zdim": 150.2055
        }
    },
    "animal_1_n24_04102017_cel1-cor-rep79": {
        "dend": {
            "area": 5342.645586187703,
            "breadth": 7,
            "contrac": 0.8727106788099928,
            "degree": 2,
            "diam": 0.579491432356354,
            "dist": 153.10014712690517,
            "length": 2533.2440280963224,
            "nbranch": 20,
            "nstem": 5,
            "nterm": 25,
            "order": 6,
            "path": 190.31457779029927,
            "seclen": 56.29431173547383,
            "volume": 1614.2583718418825,
            "xdim": 199.56279999999998,
            "ydim": 237.582,
            "zdim": 145.1996
        }
    },
    "animal_1_n24_04102017_cel1-cor-rep8": {
        "dend": {
            "area": 5750.160609732169,
            "breadth": 7,
            "contrac": 0.8743924948612909,
            "degree": 2,
            "diam": 0.5663314718453067,
            "dist": 164.61600919573405,
            "length": 2883.517185946917,
            "nbranch": 22,
            "nstem": 5,
            "nterm": 27,
            "order": 5,
            "path": 205.30757628920944,
            "seclen": 58.847289509120756,
            "volume": 1666.6499401215608,
            "xdim": 184.25900000000001,
            "ydim": 281.121,
            "zdim": 161.62310000000002
        }
    },
    "animal_1_n24_04102017_cel1-cor-rep80": {
        "dend": {
            "area": 5515.4810441610725,
            "breadth": 7,
            "contrac": 0.8839142558737415,
            "degree": 2,
            "diam": 0.5697046483961274,
            "dist": 142.96089491399385,
            "length": 2744.647674287463,
            "nbranch": 21,
            "nstem": 5,
            "nterm": 26,
            "order": 5,
            "path": 190.31457779029927,
            "seclen": 58.396759027392825,
            "volume": 1619.7915265216625,
            "xdim": 223.585,
            "ydim": 254.837,
            "zdim": 171.5319
        }
    },
    "animal_1_n24_04102017_cel1-cor-rep81": {
        "dend": {
            "area": 5927.541381917478,
            "breadth": 7,
            "contrac": 0.8824679096086413,
            "degree": 2,
            "diam": 0.5769975710652673,
            "dist": 164.61600919573405,
            "length": 2829.4326988128196,
            "nbranch": 23,
            "nstem": 5,
            "nterm": 28,
            "order": 5,
            "path": 205.30757628920944,
            "seclen": 55.47907252574156,
            "volume": 1712.768406484813,
            "xdim": 210.5279,
            "ydim": 281.121,
            "zdim": 146.6062
        }
    },
    "animal_1_n24_04102017_cel1-cor-rep82": {
        "dend": {
            "area": 5744.773477072203,
            "breadth": 7,
            "contrac": 0.8856096637880858,
            "degree": 2,
            "diam": 0.5418209728496799,
            "dist": 151.5457279200572,
            "length": 3079.341272417073,
            "nbranch": 23,
            "nstem": 5,
            "nterm": 28,
            "order": 5,
            "path": 190.31457779029927,
            "seclen": 60.37924063562888,
            "volume": 1628.1741433834225,
            "xdim": 238.513,
            "ydim": 254.837,
            "zdim": 184.13940000000002
        }
    },
    "animal_1_n24_04102017_cel1-cor-rep83": {
        "dend": {
            "area": 5200.819839289589,
            "breadth": 7,
            "contrac": 0.8760633373630842,
            "degree": 2,
            "diam": 0.5549621218684294,
            "dist": 159.4805975988929,
            "length": 2610.129924273101,
            "nbranch": 21,
            "nstem": 5,
            "nterm": 26,
            "order": 5,
            "path": 209.45353118380243,
            "seclen": 55.53467923985321,
            "volume": 1569.9283468215356,
            "xdim": 228.10500000000002,
            "ydim": 269.249,
            "zdim": 162.909
        }
    },
    "animal_1_n24_04102017_cel1-cor-rep84": {
        "dend": {
            "area": 5165.546848993826,
            "breadth": 7,
            "contrac": 0.8913898166707294,
            "degree": 2,
            "diam": 0.584605731935851,
            "dist": 147.0972138532882,
            "length": 2376.0127782909803,
            "nbranch": 18,
            "nstem": 5,
            "nterm": 23,
            "order": 5,
            "path": 190.31457779029927,
            "seclen": 57.95153117782879,
            "volume": 1600.7288611753888,
            "xdim": 175.717,
            "ydim": 269.326,
            "zdim": 150.4156
        }
    },
    "animal_1_n24_04102017_cel1-cor-rep85": {
        "dend": {
            "area": 6417.194872373519,
            "breadth": 7,
            "contrac": 0.8789581669992002,
            "degree": 2,
            "diam": 0.5358011044374877,
            "dist": 209.1612172727057,
            "length": 3339.865357787886,
            "nbranch": 27,
            "nstem": 5,
            "nterm": 32,
            "order": 6,
            "path": 246.5452373124603,
            "seclen": 56.60788742013366,
            "volume": 1739.2049604974884,
            "xdim": 265.214,
            "ydim": 322.37300000000005,
            "zdim": 147.3899
        }
    },
    "animal_1_n24_04102017_cel1-cor-rep86": {
        "dend": {
            "area": 5741.949475967824,
            "breadth": 7,
            "contrac": 0.8834376119798177,
            "degree": 2,
            "diam": 0.5407105930773887,
            "dist": 166.7820874645203,
            "length": 3022.798937094322,
            "nbranch": 22,
            "nstem": 5,
            "nterm": 27,
            "order": 6,
            "path": 214.69612370185186,
            "seclen": 61.689774226414734,
            "volume": 1635.5816249680763,
            "xdim": 192.8818,
            "ydim": 293.16499999999996,
            "zdim": 147.0809
        }
    },
    "animal_1_n24_04102017_cel1-cor-rep87": {
        "dend": {
            "area": 5450.7943226074585,
            "breadth": 7,
            "contrac": 0.8774781884475622,
            "degree": 2,
            "diam": 0.5912925732459113,
            "dist": 142.96089491399385,
            "length": 2546.3359417076445,
            "nbranch": 20,
            "nstem": 5,
            "nterm": 25,
            "order": 5,
            "path": 190.31457779029927,
            "seclen": 56.58524314905877,
            "volume": 1639.331387810493,
            "xdim": 198.4203,
            "ydim": 235.30200000000002,
            "zdim": 159.8162
        }
    },
    "animal_1_n24_04102017_cel1-cor-rep88": {
        "dend": {
            "area": 5406.602274592196,
            "breadth": 7,
            "contrac": 0.8798740024201572,
            "degree": 2,
            "diam": 0.5573198322686381,
            "dist": 142.96089491399385,
            "length": 2651.504560798807,
            "nbranch": 20,
            "nstem": 5,
            "nterm": 25,
            "order": 5,
            "path": 190.31457779029927,
            "seclen": 58.92232357330682,
            "volume": 1615.4928179808117,
            "xdim": 194.9624,
            "ydim": 242.92700000000002,
            "zdim": 141.6526
        }
    },
    "animal_1_n24_04102017_cel1-cor-rep89": {
        "dend": {
            "area": 5974.298455769085,
            "breadth": 7,
            "contrac": 0.8804122215717023,
            "degree": 2,
            "diam": 0.545333799545239,
            "dist": 217.9775916305619,
            "length": 3137.4180227473407,
            "nbranch": 25,
            "nstem": 5,
            "nterm": 30,
            "order": 6,
            "path": 255.38152999351558,
            "seclen": 57.04396404995165,
            "volume": 1674.2953559211435,
            "xdim": 218.702,
            "ydim": 365.461,
            "zdim": 186.6567
        }
    },
    "animal_1_n24_04102017_cel1-cor-rep9": {
        "dend": {
            "area": 5225.655540016667,
            "breadth": 7,
            "contrac": 0.8805204344079389,
            "degree": 2,
            "diam": 0.5845070397875702,
            "dist": 151.14368371599258,
            "length": 2541.460193708531,
            "nbranch": 18,
            "nstem": 5,
            "nterm": 23,
            "order": 5,
            "path": 190.31457779029927,
            "seclen": 61.98683399289099,
            "volume": 1587.4841093469174,
            "xdim": 196.7188,
            "ydim": 263.626,
            "zdim": 161.62310000000002
        }
    },
    "animal_1_n24_04102017_cel1-cor-rep90": {
        "dend": {
            "area": 5820.670263930911,
            "breadth": 7,
            "contrac": 0.8830240686365072,
            "degree": 2,
            "diam": 0.5747857641394976,
            "dist": 199.71421724303957,
            "length": 2870.6207827607245,
            "nbranch": 21,
            "nstem": 5,
            "nterm": 26,
            "order": 5,
            "path": 253.51228079157332,
            "seclen": 61.077037931079246,
            "volume": 1672.3044380972347,
            "xdim": 213.4373,
            "ydim": 289.734,
            "zdim": 152.6282
        }
    },
    "animal_1_n24_04102017_cel1-cor-rep91": {
        "dend": {
            "area": 6068.642679798339,
            "breadth": 10,
            "contrac": 0.8843682538933448,
            "degree": 2,
            "diam": 0.5475443151403734,
            "dist": 243.69764573596112,
            "length": 3177.7242040066417,
            "nbranch": 24,
            "nstem": 5,
            "nterm": 29,
            "order": 8,
            "path": 279.9519348497326,
            "seclen": 59.9570604529555,
            "volume": 1677.7995714163872,
            "xdim": 250.752,
            "ydim": 385.28700000000003,
            "zdim": 152.6282
        }
    },
    "animal_1_n24_04102017_cel1-cor-rep92": {
        "dend": {
            "area": 6327.933658866037,
            "breadth": 7,
            "contrac": 0.8794623946448996,
            "degree": 2,
            "diam": 0.5780376290631126,
            "dist": 176.35127136499472,
            "length": 3116.680246737723,
            "nbranch": 23,
            "nstem": 5,
            "nterm": 28,
            "order": 5,
            "path": 225.18101274628057,
            "seclen": 61.11137738701417,
            "volume": 1757.8234301344621,
            "xdim": 185.7529,
            "ydim": 283.152,
            "zdim": 157.5359
        }
    },
    "animal_1_n24_04102017_cel1-cor-rep93": {
        "dend": {
            "area": 5976.713284212401,
            "breadth": 7,
            "contrac": 0.8838455437027415,
            "degree": 2,
            "diam": 0.5530354345937619,
            "dist": 217.9775916305619,
            "length": 3024.311175077473,
            "nbranch": 23,
            "nstem": 5,
            "nterm": 28,
            "order": 6,
            "path": 273.3886923002496,
            "seclen": 59.30021911916614,
            "volume": 1688.8323503759216,
            "xdim": 241.676,
            "ydim": 420.77,
            "zdim": 176.17669999999998
        }
    },
    "animal_1_n24_04102017_cel1-cor-rep94": {
        "dend": {
            "area": 5518.8846774133335,
            "breadth": 7,
            "contrac": 0.8828326272881456,
            "degree": 2,
            "diam": 0.5324641914230799,
            "dist": 142.96089491399385,
            "length": 2798.0022713967087,
            "nbranch": 23,
            "nstem": 5,
            "nterm": 28,
            "order": 5,
            "path": 190.31457779029927,
            "seclen": 54.86278963522958,
            "volume": 1619.1643893435903,
            "xdim": 223.585,
            "ydim": 237.05200000000002,
            "zdim": 171.5319
        }
    },
    "animal_1_n24_04102017_cel1-cor-rep95": {
        "dend": {
            "area": 5235.250524895184,
            "breadth": 7,
            "contrac": 0.8870968192955151,
            "degree": 2,
            "diam": 0.5588675900231506,
            "dist": 151.03153413790776,
            "length": 2591.1469991397626,
            "nbranch": 21,
            "nstem": 5,
            "nterm": 26,
            "order": 5,
            "path": 190.31457779029927,
            "seclen": 55.13078721573963,
            "volume": 1576.8986620165006,
            "xdim": 175.717,
            "ydim": 271.121,
            "zdim": 132.2624
        }
    },
    "animal_1_n24_04102017_cel1-cor-rep96": {
        "dend": {
            "area": 5739.3401771519775,
            "breadth": 7,
            "contrac": 0.8815030408350626,
            "degree": 2,
            "diam": 0.5567387464759741,
            "dist": 158.04052534505195,
            "length": 2987.0891028155465,
            "nbranch": 21,
            "nstem": 5,
            "nterm": 26,
            "order": 5,
            "path": 203.75285828718415,
            "seclen": 63.5550872939478,
            "volume": 1637.333047797461,
            "xdim": 247.90200000000002,
            "ydim": 285.745,
            "zdim": 194.2027
        }
    },
    "animal_1_n24_04102017_cel1-cor-rep97": {
        "dend": {
            "area": 5824.005976986597,
            "breadth": 7,
            "contrac": 0.8734188024296511,
            "degree": 2,
            "diam": 0.5711376815842519,
            "dist": 142.96089491399385,
            "length": 2802.551550092618,
            "nbranch": 22,
            "nstem": 5,
            "nterm": 27,
            "order": 5,
            "path": 190.31457779029927,
            "seclen": 57.1949295937269,
            "volume": 1698.5570584050076,
            "xdim": 219.03300000000002,
            "ydim": 226.161,
            "zdim": 166.3773
        }
    },
    "animal_1_n24_04102017_cel1-cor-rep98": {
        "dend": {
            "area": 5254.5228919833635,
            "breadth": 7,
            "contrac": 0.8795691869257394,
            "degree": 2,
            "diam": 0.5976564055519815,
            "dist": 161.14827484433118,
            "length": 2416.5001476288708,
            "nbranch": 18,
            "nstem": 5,
            "nterm": 23,
            "order": 6,
            "path": 191.7033678415073,
            "seclen": 58.93902799094807,
            "volume": 1616.4333298390768,
            "xdim": 201.0198,
            "ydim": 261.308,
            "zdim": 150.4156
        }
    },
    "animal_1_n24_04102017_cel1-cor-rep99": {
        "dend": {
            "area": 5845.083084099198,
            "breadth": 7,
            "contrac": 0.8806943147708982,
            "degree": 2,
            "diam": 0.6044791512154224,
            "dist": 156.47370359883197,
            "length": 2724.8579590310355,
            "nbranch": 20,
            "nstem": 5,
            "nterm": 25,
            "order": 5,
            "path": 192.10671254644404,
            "seclen": 60.552399089578564,
            "volume": 1723.8518139792104,
            "xdim": 255.32,
            "ydim": 251.97899999999998,
            "zdim": 166.3773
        }
    }
}